py_str_utils/__init__.py
py_str_utils/length.py
py_str_utils-0.0.1.dist-info/METADATA
py_str_utils-0.0.1.dist-info/WHEEL
py_str_utils-0.0.1.dist-info/top_level.txt
py_str_utils-0.0.1.dist-info/RECORD
