Metadata-Version: 2.1
Name: py_str_utils
Version: 0.0.1
Summary: Str utils
Author: fernandocode
Author-email: lealfernandoleal@gmail.com
Requires-Python: >=3.8
